saradirmaker/__init__.py
saradirmaker/saradirmaker.py
saradirmaker-0.0.1.dist-info/METADATA
saradirmaker-0.0.1.dist-info/WHEEL
saradirmaker-0.0.1.dist-info/entry_points.txt
saradirmaker-0.0.1.dist-info/top_level.txt
saradirmaker-0.0.1.dist-info/RECORD
