Metadata-Version: 2.1
Name: saradirmaker
Version: 0.0.1
Summary: It is about file maker cli tool
Home-page: UNKNOWN
Author: Saranya
Author-email: saranyaveeradurai@gmail.com
License: UNKNOWN
Platform: UNKNOWN
Requires-Dist: pandas
